LICENSE
MANIFEST.in
README.rst
flask_turbolinks.py
setup.py
Flask_Turbolinks.egg-info/PKG-INFO
Flask_Turbolinks.egg-info/SOURCES.txt
Flask_Turbolinks.egg-info/dependency_links.txt
Flask_Turbolinks.egg-info/not-zip-safe
Flask_Turbolinks.egg-info/requires.txt
Flask_Turbolinks.egg-info/top_level.txt