Metadata-Version: 1.0
Name: Flask-Turbolinks
Version: 0.1.3
Summary: Turbolinks for Flask.
Home-page: https://github.com/lepture/flask-turbolinks
Author: Hsiaoming Yang
Author-email: me@lepture.com
License: BSD
Platform: any
Classifier: Development Status :: 4 - Beta
Classifier: Environment :: Web Environment
Classifier: Intended Audience :: Developers
Classifier: License :: OSI Approved :: BSD License
Classifier: Operating System :: OS Independent
Classifier: Programming Language :: Python
Classifier: Topic :: Internet :: WWW/HTTP :: Dynamic Content
Classifier: Topic :: Software Development :: Libraries :: Python Modules
